Workbook

Sheet A4_Budget_vs_Actual
A1: VEDIC TECHNOLOGIES & RETAIL SOLUTIONS PVT. LTD. - PUNE, MAHARASHTRA
A2: Assignment 4: Financial Data Analysis & Budget Planner Case — FY 2025-26 Monthly Financial Summary (in INR ₹)
A4: 1. MONTHLY INCOME SUMMARY (ACTUAL VS. BUDGET)
A5: Income Category | B5: Budgeted Income (₹) | C5: Actual Income (₹) | D5: Variance (₹) | E5: Variance % | F5: Status
A6: Software Services & IT Consulting | B6: 450000 | C6: 485000 | D6: =C6-B6 -> 35000 | E6: =D6/B6 -> 0.077777778 | F6: =IF(D6>=0,"Favorable","Unfavorable") -> Favorable
A7: Retail Store Sales (Pune & Mumbai) | B7: 380000 | C7: 362000 | D7: =C7-B7 -> -18000 | E7: =D7/B7 -> -0.047368421 | F7: =IF(D7>=0,"Favorable","Unfavorable") -> Unfavorable
A8: Annual Maintenance Contracts (AMC) | B8: 150000 | C8: 160000 | D8: =C8-B8 -> 10000 | E8: =D8/B8 -> 0.066666667 | F8: =IF(D8>=0,"Favorable","Unfavorable") -> Favorable
A9: Corporate Training & Workshops | B9: 120000 | C9: 135000 | D9: =C9-B9 -> 15000 | E9: =D9/B9 -> 0.125 | F9: =IF(D9>=0,"Favorable","Unfavorable") -> Favorable
A10: Interest Income & Fixed Deposits | B10: 25000 | C10: 26500 | D10: =C10-B10 -> 1500 | E10: =D10/B10 -> 0.06 | F10: =IF(D10>=0,"Favorable","Unfavorable") -> Favorable
A11: Total Monthly Income | B11: =SUM(B6:B10) -> 1125000 | C11: =SUM(C6:C10) -> 1168500 | D11: =C11-B11 -> 43500 | E11: =D11/B11 -> 0.038666667 | F11: =IF(D11>=0,"Favorable","Unfavorable") -> Favorable
A13: 2. MONTHLY OPERATING EXPENDITURE (ACTUAL VS. BUDGET)
A14: Expense Category | B14: Budgeted Expense (₹) | C14: Actual Expense (₹) | D14: Variance / Saving (₹) | E14: Variance % | F14: Budget Status
A15: Employee Salaries & Staff Benefits | B15: 420000 | C15: 428000 | D15: =B15-C15 -> -8000 | E15: =(C15-B15)/B15 -> 0.019047619 | F15: =IF(C15>B15,"OVER BUDGET","UNDER BUDGET") -> OVER BUDGET
A16: Office Rent & Commercial Premises Lease | B16: 110000 | C16: 110000 | D16: =B16-C16 -> 0 | E16: =(C16-B16)/B16 -> 0 | F16: =IF(C16>B16,"OVER BUDGET","UNDER BUDGET") -> UNDER BUDGET
A17: Marketing, Digital Ads & Branding | B17: 85000 | C17: 98500 | D17: =B17-C17 -> -13500 | E17: =(C17-B17)/B17 -> 0.15882353 | F17: =IF(C17>B17,"OVER BUDGET","UNDER BUDGET") -> OVER BUDGET
A18: Client Travel & Business Promotion | B18: 45000 | C18: 39000 | D18: =B18-C18 -> 6000 | E18: =(C18-B18)/B18 -> -0.13333333 | F18: =IF(C18>B18,"OVER BUDGET","UNDER BUDGET") -> UNDER BUDGET
A19: Electricity, Water & Utilities | B19: 28000 | C19: 31200 | D19: =B19-C19 -> -3200 | E19: =(C19-B19)/B19 -> 0.11428571 | F19: =IF(C19>B19,"OVER BUDGET","UNDER BUDGET") -> OVER BUDGET
A20: Software Licenses & IT Cloud Infrastructure | B20: 55000 | C20: 52000 | D20: =B20-C20 -> 3000 | E20: =(C20-B20)/B20 -> -0.054545455 | F20: =IF(C20>B20,"OVER BUDGET","UNDER BUDGET") -> UNDER BUDGET
A21: Accounting, GST Compliance & Legal Fees | B21: 22000 | C21: 22000 | D21: =B21-C21 -> 0 | E21: =(C21-B21)/B21 -> 0 | F21: =IF(C21>B21,"OVER BUDGET","UNDER BUDGET") -> UNDER BUDGET
A22: Logistics & Local Conveyance | B22: 35000 | C22: 38500 | D22: =B22-C22 -> -3500 | E22: =(C22-B22)/B22 -> 0.1 | F22: =IF(C22>B22,"OVER BUDGET","UNDER BUDGET") -> OVER BUDGET
A23: Office Supplies & Miscellaneous Expenses | B23: 20000 | C23: 18400 | D23: =B23-C23 -> 1600 | E23: =(C23-B23)/B23 -> -0.08 | F23: =IF(C23>B23,"OVER BUDGET","UNDER BUDGET") -> UNDER BUDGET
A24: Total Operating Expenditure | B24: =SUM(B15:B23) -> 820000 | C24: =SUM(C15:C23) -> 837600 | D24: =B24-C24 -> -17600 | E24: =(C24-B24)/B24 -> 0.021463415 | F24: =IF(C24>B24,"OVER BUDGET","UNDER BUDGET") -> OVER BUDGET
A26: 3. EXECUTIVE FINANCIAL PERFORMANCE SUMMARY & NET MARGIN
A27: Financial Metric | B27: Budgeted / Target (₹) | C27: Actual Performance (₹) | D27: Net Variance (₹) | E27: Performance Ratio / Status
A28: Total Operating Revenue / Income | B28: =B11 -> 1125000 | C28: =C11 -> 1168500 | D28: =C11-B11 -> 43500 | E28: =IF(C11>=B11,"Target Met","Below Target") -> Target Met
A29: Total Operating Expenditure | B29: =B24 -> 820000 | C29: =C24 -> 837600 | D29: =B24-C24 -> -17600 | E29: =IF(C24<=B24,"Controlled","Overspending") -> Overspending
A30: Net Monthly Profit / Savings | B30: =B28-B29 -> 305000 | C30: =C28-C29 -> 330900 | D30: =C30-B30 -> 25900 | E30: =IF(C30>0,"Profitable","Net Deficit") -> Profitable
A31: Operating Savings Margin % | B31: =B30/B28 -> 0.27111111 | C31: =C30/C28 -> 0.28318357 | D31: =C31-B31 -> 0.012072458 | E31: =IF(C31>=B31,"Margin Expanded","Margin Contracted") -> Margin Expanded

Sheet A4_Monthly_Trend
A1: VEDIC TECHNOLOGIES & RETAIL SOLUTIONS PVT. LTD. - 6-MONTH FINANCIAL TREND ANALYSIS
A2: Assignment 4: Historical Income vs. Expenditure Tracking & Margin Analysis (Jan 2026 - Jun 2026)
A5: Financial Metric (INR ₹) | B5: Jan-26 | C5: Feb-26 | D5: Mar-26 | E5: Apr-26 | F5: May-26 | G5: Jun-26 | H5: 6-Month Total | I5: Monthly Average
A6: Total Income / Revenue | B6: 1080000 | C6: 1150000 | D6: 1220000 | E6: 1168500 | F6: 1250000 | G6: 1310000 | H6: =SUM(B6:G6) -> 7178500 | I6: =AVERAGE(B6:G6) -> 1196416.7
A7: Salaries & Staff Costs | B7: 410000 | C7: 415000 | D7: 420000 | E7: 428000 | F7: 435000 | G7: 440000 | H7: =SUM(B7:G7) -> 2548000 | I7: =AVERAGE(B7:G7) -> 424666.67
A8: Office Rent & Premises Lease | B8: 110000 | C8: 110000 | D8: 110000 | E8: 110000 | F8: 110000 | G8: 110000 | H8: =SUM(B8:G8) -> 660000 | I8: =AVERAGE(B8:G8) -> 110000
A9: Marketing & Promotions | B9: 75000 | C9: 82000 | D9: 95000 | E9: 98500 | F9: 90000 | G9: 105000 | H9: =SUM(B9:G9) -> 545500 | I9: =AVERAGE(B9:G9) -> 90916.667
A10: Travel & Client Visits | B10: 35000 | C10: 42000 | D10: 48000 | E10: 39000 | F10: 44000 | G10: 52000 | H10: =SUM(B10:G10) -> 260000 | I10: =AVERAGE(B10:G10) -> 43333.333
A11: Utilities & Maintenance | B11: 29000 | C11: 30000 | D11: 31000 | E11: 31200 | F11: 32000 | G11: 33500 | H11: =SUM(B11:G11) -> 186700 | I11: =AVERAGE(B11:G11) -> 31116.667
A12: Software & IT Infrastructure | B12: 48000 | C12: 50000 | D12: 51000 | E12: 52000 | F12: 53000 | G12: 54000 | H12: =SUM(B12:G12) -> 308000 | I12: =AVERAGE(B12:G12) -> 51333.333
A13: Other Operational Expenses | B13: 55000 | C13: 58000 | D13: 62000 | E13: 78900 | F13: 61000 | G13: 64000 | H13: =SUM(B13:G13) -> 378900 | I13: =AVERAGE(B13:G13) -> 63150
A14: Total Operating Expenditure | B14: =SUM(B7:B13) -> 762000 | C14: =SUM(C7:C13) -> 787000 | D14: =SUM(D7:D13) -> 817000 | E14: =SUM(E7:E13) -> 837600 | F14: =SUM(F7:F13) -> 825000 | G14: =SUM(G7:G13) -> 858500 | H14: =SUM(H7:H13) -> 4887100 | I14: =AVERAGE(B14:G14) -> 814516.67
A15: Net Monthly Profit / Savings | B15: =B6-B14 -> 318000 | C15: =C6-C14 -> 363000 | D15: =D6-D14 -> 403000 | E15: =E6-E14 -> 330900 | F15: =F6-F14 -> 425000 | G15: =G6-G14 -> 451500 | H15: =H6-H14 -> 2291400 | I15: =AVERAGE(B15:G15) -> 381900
A16: Net Savings Margin % | B16: =B15/B6 -> 0.29444444 | C16: =C15/C6 -> 0.31565217 | D16: =D15/D6 -> 0.33032787 | E16: =E15/E6 -> 0.28318357 | F16: =F15/F6 -> 0.34 | G16: =G15/G6 -> 0.34465649 | H16: =H15/H6 -> 0.31920318 | I16: =I15/I6 -> 0.31920318

Sheet IBC_Employee_Performance
A1: AARAV RETAIL & LIFESTYLE INDIA LTD. - NATIONAL HR & SALES MANAGEMENT
A2: Integrated Business Case: Employee Performance Scoring, Sales Quota Attainment & Bonus Calculation
A4: Total Sales Target (₹) | C4: Total Sales Achieved (₹) | E4: Avg Target Attainment | G4: Top Performers Count | I4: Total Performance Bonus (₹)
A5: =SUM(E9:E23) -> 15200000 | C5: =SUM(F9:F23) -> 16020000 | E5: =AVERAGE(G9:G23) -> 1.049233 | G5: =COUNTIF(K9:K23,"Top Performer") -> 12 | I5: =SUM(L9:L23) -> 750400
A7: EMPLOYEE PERFORMANCE SCORECARD & BONUS EVALUATION (FY 2025-26 - Q3)
A8: Emp ID | B8: Employee Name (India) | C8: Department / Vertical | D8: Base Location (City) | E8: Monthly Target (₹) | F8: Sales Achieved (₹) | G8: Attainment % | H8: CSAT Score (10) | I8: Manager Rating (10) | J8: Composite Score (100) | K8: Performance Band | L8: Incentive Bonus (₹)
A9: EMP-101 | B9: Aarav Sharma | C9: Enterprise Retail | D9: Mumbai | E9: 1200000 | F9: 1380000 | G9: =F9/E9 -> 1.15 | H9: 9.2 | I9: 9 | J9: =ROUND((MIN(G9, 1.15)*60) + (H9/10)*20 + (I9/10)*20, 1) -> 105.4 | K9: =IF(J9>=90,"Top Performer",IF(J9>=80,"Exceeds Expectations",IF(J9>=70,"Meets Expectations","Needs Improvement"))) -> Top Performer | L9: =IF(K9="Top Performer",F9*0.05,IF(K9="Exceeds Expectations",F9*0.03,IF(K9="Meets Expectations",F9*0.01,0))) -> 69000
A10: EMP-102 | B10: Priya Nair | C10: Key Accounts | D10: Bengaluru | E10: 1000000 | F10: 1120000 | G10: =F10/E10 -> 1.12 | H10: 9.5 | I10: 9.2 | J10: =ROUND((MIN(G10, 1.15)*60) + (H10/10)*20 + (I10/10)*20, 1) -> 104.6 | K10: =IF(J10>=90,"Top Performer",IF(J10>=80,"Exceeds Expectations",IF(J10>=70,"Meets Expectations","Needs Improvement"))) -> Top Performer | L10: =IF(K10="Top Performer",F10*0.05,IF(K10="Exceeds Expectations",F10*0.03,IF(K10="Meets Expectations",F10*0.01,0))) -> 56000
A11: EMP-103 | B11: Rohan Mehta | C11: B2B Sales | D11: Pune | E11: 850000 | F11: 890000 | G11: =F11/E11 -> 1.0470588 | H11: 8.8 | I11: 8.5 | J11: =ROUND((MIN(G11, 1.15)*60) + (H11/10)*20 + (I11/10)*20, 1) -> 97.4 | K11: =IF(J11>=90,"Top Performer",IF(J11>=80,"Exceeds Expectations",IF(J11>=70,"Meets Expectations","Needs Improvement"))) -> Top Performer | L11: =IF(K11="Top Performer",F11*0.05,IF(K11="Exceeds Expectations",F11*0.03,IF(K11="Meets Expectations",F11*0.01,0))) -> 44500
A12: EMP-104 | B12: Neha Kulkarni | C12: Regional Retail | D12: Pune | E12: 900000 | F12: 945000 | G12: =F12/E12 -> 1.05 | H12: 8.9 | I12: 8.7 | J12: =ROUND((MIN(G12, 1.15)*60) + (H12/10)*20 + (I12/10)*20, 1) -> 98.2 | K12: =IF(J12>=90,"Top Performer",IF(J12>=80,"Exceeds Expectations",IF(J12>=70,"Meets Expectations","Needs Improvement"))) -> Top Performer | L12: =IF(K12="Top Performer",F12*0.05,IF(K12="Exceeds Expectations",F12*0.03,IF(K12="Meets Expectations",F12*0.01,0))) -> 47250
A13: EMP-105 | B13: Aditya Verma | C13: Enterprise Retail | D13: Delhi | E13: 1500000 | F13: 1620000 | G13: =F13/E13 -> 1.08 | H13: 9.1 | I13: 9 | J13: =ROUND((MIN(G13, 1.15)*60) + (H13/10)*20 + (I13/10)*20, 1) -> 101 | K13: =IF(J13>=90,"Top Performer",IF(J13>=80,"Exceeds Expectations",IF(J13>=70,"Meets Expectations","Needs Improvement"))) -> Top Performer | L13: =IF(K13="Top Performer",F13*0.05,IF(K13="Exceeds Expectations",F13*0.03,IF(K13="Meets Expectations",F13*0.01,0))) -> 81000
A14: EMP-106 | B14: Vikram Deshmukh | C14: Regional Retail | D14: Mumbai | E14: 1100000 | F14: 980000 | G14: =F14/E14 -> 0.89090909 | H14: 8 | I14: 7.8 | J14: =ROUND((MIN(G14, 1.15)*60) + (H14/10)*20 + (I14/10)*20, 1) -> 85.1 | K14: =IF(J14>=90,"Top Performer",IF(J14>=80,"Exceeds Expectations",IF(J14>=70,"Meets Expectations","Needs Improvement"))) -> Exceeds Expectations | L14: =IF(K14="Top Performer",F14*0.05,IF(K14="Exceeds Expectations",F14*0.03,IF(K14="Meets Expectations",F14*0.01,0))) -> 29400
A15: EMP-107 | B15: Pooja Iyer | C15: Key Accounts | D15: Chennai | E15: 950000 | F15: 1045000 | G15: =F15/E15 -> 1.1 | H15: 9.3 | I15: 9 | J15: =ROUND((MIN(G15, 1.15)*60) + (H15/10)*20 + (I15/10)*20, 1) -> 102.6 | K15: =IF(J15>=90,"Top Performer",IF(J15>=80,"Exceeds Expectations",IF(J15>=70,"Meets Expectations","Needs Improvement"))) -> Top Performer | L15: =IF(K15="Top Performer",F15*0.05,IF(K15="Exceeds Expectations",F15*0.03,IF(K15="Meets Expectations",F15*0.01,0))) -> 52250
A16: EMP-108 | B16: Sneha Patil | C16: B2B Sales | D16: Hyderabad | E16: 1050000 | F16: 1100000 | G16: =F16/E16 -> 1.047619 | H16: 8.7 | I16: 8.8 | J16: =ROUND((MIN(G16, 1.15)*60) + (H16/10)*20 + (I16/10)*20, 1) -> 97.9 | K16: =IF(J16>=90,"Top Performer",IF(J16>=80,"Exceeds Expectations",IF(J16>=70,"Meets Expectations","Needs Improvement"))) -> Top Performer | L16: =IF(K16="Top Performer",F16*0.05,IF(K16="Exceeds Expectations",F16*0.03,IF(K16="Meets Expectations",F16*0.01,0))) -> 55000
A17: EMP-109 | B17: Amit Kulkarni | C17: Regional Retail | D17: Ahmedabad | E17: 800000 | F17: 740000 | G17: =F17/E17 -> 0.925 | H17: 7.5 | I17: 7.2 | J17: =ROUND((MIN(G17, 1.15)*60) + (H17/10)*20 + (I17/10)*20, 1) -> 84.9 | K17: =IF(J17>=90,"Top Performer",IF(J17>=80,"Exceeds Expectations",IF(J17>=70,"Meets Expectations","Needs Improvement"))) -> Exceeds Expectations | L17: =IF(K17="Top Performer",F17*0.05,IF(K17="Exceeds Expectations",F17*0.03,IF(K17="Meets Expectations",F17*0.01,0))) -> 22200
A18: EMP-110 | B18: Anjali Deshmukh | C18: Enterprise Retail | D18: Kolkata | E18: 900000 | F18: 960000 | G18: =F18/E18 -> 1.0666667 | H18: 8.8 | I18: 8.9 | J18: =ROUND((MIN(G18, 1.15)*60) + (H18/10)*20 + (I18/10)*20, 1) -> 99.4 | K18: =IF(J18>=90,"Top Performer",IF(J18>=80,"Exceeds Expectations",IF(J18>=70,"Meets Expectations","Needs Improvement"))) -> Top Performer | L18: =IF(K18="Top Performer",F18*0.05,IF(K18="Exceeds Expectations",F18*0.03,IF(K18="Meets Expectations",F18*0.01,0))) -> 48000
A19: EMP-111 | B19: Karthik Rajan | C19: Key Accounts | D19: Bengaluru | E19: 1150000 | F19: 1265000 | G19: =F19/E19 -> 1.1 | H19: 9.4 | I19: 9.1 | J19: =ROUND((MIN(G19, 1.15)*60) + (H19/10)*20 + (I19/10)*20, 1) -> 103 | K19: =IF(J19>=90,"Top Performer",IF(J19>=80,"Exceeds Expectations",IF(J19>=70,"Meets Expectations","Needs Improvement"))) -> Top Performer | L19: =IF(K19="Top Performer",F19*0.05,IF(K19="Exceeds Expectations",F19*0.03,IF(K19="Meets Expectations",F19*0.01,0))) -> 63250
A20: EMP-112 | B20: Divya Joshi | C20: Regional Retail | D20: Jaipur | E20: 700000 | F20: 735000 | G20: =F20/E20 -> 1.05 | H20: 8.6 | I20: 8.5 | J20: =ROUND((MIN(G20, 1.15)*60) + (H20/10)*20 + (I20/10)*20, 1) -> 97.2 | K20: =IF(J20>=90,"Top Performer",IF(J20>=80,"Exceeds Expectations",IF(J20>=70,"Meets Expectations","Needs Improvement"))) -> Top Performer | L20: =IF(K20="Top Performer",F20*0.05,IF(K20="Exceeds Expectations",F20*0.03,IF(K20="Meets Expectations",F20*0.01,0))) -> 36750
... A23: EMP-115 | B23: Tanvi Rao | C23: Key Accounts | D23: Hyderabad | E23: 950000 | F23: 1020000 | G23: =F23/E23 -> 1.0736842 | H23: 9.1 | I23: 9 | J23: =ROUND((MIN(G23, 1.15)*60) + (H23/10)*20 + (I23/10)*20, 1) -> 100.6 | K23: =IF(J23>=90,"Top Performer",IF(J23>=80,"Exceeds Expectations",IF(J23>=70,"Meets Expectations","Needs Improvement"))) -> Top Performer | L23: =IF(K23="Top Performer",F23*0.05,IF(K23="Exceeds Expectations",F23*0.03,IF(K23="Meets Expectations",F23*0.01,0))) -> 51000
A24: Total / Average | E24: =SUM(E9:E23) -> 15200000 | F24: =SUM(F9:F23) -> 16020000 | G24: =F24/E24 -> 1.0539474 | H24: =AVERAGE(H9:H23) -> 8.78 | I24: =AVERAGE(I9:I23) -> 8.6266667 | J24: =AVERAGE(J9:J23) -> 97.773333 | K24: =COUNTIF(K9:K23,"Top Performer") & " Top Performers" -> 12 Top Performers | L24: =SUM(L9:L23) -> 750400

Sheet IBC_Sales_and_Geography
A1: AARAV RETAIL & LIFESTYLE INDIA LTD. - REGIONAL SALES & AI GEOGRAPHY DATA ENRICHMENT
A2: Integrated Business Case: Geography Data Type Enrichment, Regional Revenue Ranking & Inventory Replenishment Monitor
A4: 📌 EXCEL AI-POWERED GEOGRAPHY DATA TYPE ENRICHMENT NOTE:
A5: In Microsoft Excel, selecting Indian City names and clicking 'Data > Geography' converts text into AI-linked data types. The columns below (State / UT, City Tier, Population, Administrative Region) model the live metadata pulled from Excel's Bing/AI Knowledge Graph to enrich sales analytics without manual external lookups.
A7: 1. REGIONAL RETAIL PERFORMANCE & GEOGRAPHY DATA ENRICHMENT (INDIA)
A8: City [AI Geography] | B8: State / UT [Enriched] | C8: City Tier [Enriched] | D8: Population (Lakhs) [AI] | E8: Active Retail Stores | F8: Monthly Units Sold | G8: Monthly Revenue (₹) | H8: Avg Store Revenue (₹) | I8: YoY Growth % | J8: Regional Growth Status
A9: Mumbai | B9: Maharashtra | C9: Tier 1 | D9: 210 | E9: 18 | F9: 14500 | G9: 34800000 | H9: =G9/E9 -> 1933333.3 | I9: 0.18 | J9: =IF(I9>=0.18,"High Growth Leader",IF(I9>=0.12,"Steady Expand","Mature / Monitor")) -> High Growth Leader
A10: Delhi NCR | B10: Delhi | C10: Tier 1 | D10: 310 | E10: 22 | F10: 16800 | G10: 38500000 | H10: =G10/E10 -> 1750000 | I10: 0.15 | J10: =IF(I10>=0.18,"High Growth Leader",IF(I10>=0.12,"Steady Expand","Mature / Monitor")) -> Steady Expand
A11: Bengaluru | B11: Karnataka | C11: Tier 1 | D11: 130 | E11: 15 | F11: 12400 | G11: 29600000 | H11: =G11/E11 -> 1973333.3 | I11: 0.22 | J11: =IF(I11>=0.18,"High Growth Leader",IF(I11>=0.12,"Steady Expand","Mature / Monitor")) -> High Growth Leader
A12: Pune | B12: Maharashtra | C12: Tier 1 | D12: 75 | E12: 10 | F12: 8900 | G12: 19500000 | H12: =G12/E12 -> 1950000 | I12: 0.19 | J12: =IF(I12>=0.18,"High Growth Leader",IF(I12>=0.12,"Steady Expand","Mature / Monitor")) -> High Growth Leader
A13: Hyderabad | B13: Telangana | C13: Tier 1 | D13: 105 | E13: 12 | F13: 9800 | G13: 23200000 | H13: =G13/E13 -> 1933333.3 | I13: 0.21 | J13: =IF(I13>=0.18,"High Growth Leader",IF(I13>=0.12,"Steady Expand","Mature / Monitor")) -> High Growth Leader
A14: Chennai | B14: Tamil Nadu | C14: Tier 1 | D14: 115 | E14: 11 | F14: 9200 | G14: 21800000 | H14: =G14/E14 -> 1981818.2 | I14: 0.14 | J14: =IF(I14>=0.18,"High Growth Leader",IF(I14>=0.12,"Steady Expand","Mature / Monitor")) -> Steady Expand
A15: Ahmedabad | B15: Gujarat | C15: Tier 1 | D15: 85 | E15: 8 | F15: 6500 | G15: 14200000 | H15: =G15/E15 -> 1775000 | I15: 0.11 | J15: =IF(I15>=0.18,"High Growth Leader",IF(I15>=0.12,"Steady Expand","Mature / Monitor")) -> Mature / Monitor
A16: Kolkata | B16: West Bengal | C16: Tier 1 | D16: 150 | E16: 9 | F16: 7100 | G16: 15800000 | H16: =G16/E16 -> 1755555.6 | I16: 0.09 | J16: =IF(I16>=0.18,"High Growth Leader",IF(I16>=0.12,"Steady Expand","Mature / Monitor")) -> Mature / Monitor
A17: Jaipur | B17: Rajasthan | C17: Tier 2 | D17: 40 | E17: 6 | F17: 4200 | G17: 8900000 | H17: =G17/E17 -> 1483333.3 | I17: 0.16 | J17: =IF(I17>=0.18,"High Growth Leader",IF(I17>=0.12,"Steady Expand","Mature / Monitor")) -> Steady Expand
A18: Surat | B18: Gujarat | C18: Tier 2 | D18: 65 | E18: 7 | F18: 5100 | G18: 11200000 | H18: =G18/E18 -> 1600000 | I18: 0.13 | J18: =IF(I18>=0.18,"High Growth Leader",IF(I18>=0.12,"Steady Expand","Mature / Monitor")) -> Steady Expand
A19: National Retail Total / Avg | D19: =SUM(D9:D18) -> 1285 | E19: =SUM(E9:E18) -> 118 | F19: =SUM(F9:F18) -> 94500 | G19: =SUM(G9:G18) -> 217500000 | H19: =G19/E19 -> 1843220.3 | I19: =AVERAGE(I9:I18) -> 0.158 | J19: =COUNTIF(J9:J18,"High Growth Leader") & " High Growth Cities" -> 4 High Growth Cities
A21: 2. AI RETAIL INVENTORY MONITOR & LOW-STOCK REORDER ALERT SYSTEM
A22: SKU Code | B22: Indian Product Description | C22: Category / Artisan Craft | D22: Current Stock (Units) | E22: Reorder Threshold | F22: Economic Order Qty (EOQ) | G22: Unit Price (₹) | H22: Total Inventory Value (₹) | I22: Replenishment Status Alert
A23: SKU-501 | B23: Kanchipuram Pure Silk Saree | C23: Traditional Apparel | D23: 18 | E23: 25 | F23: 50 | G23: 18500 | H23: =D23*G23 -> 333000 | I23: =IF(D23<=E23,"CRITICAL - REORDER NOW",IF(D23<=E23*1.25,"LOW STOCK - MONITOR","OPTIMAL STOCK")) -> CRITICAL - REORDER NOW
A24: SKU-502 | B24: Handwoven Pashmina Wool Shawl | C24: Luxury Accessories | D24: 42 | E24: 30 | F24: 40 | G24: 12000 | H24: =D24*G24 -> 504000 | I24: =IF(D24<=E24,"CRITICAL - REORDER NOW",IF(D24<=E24*1.25,"LOW STOCK - MONITOR","OPTIMAL STOCK")) -> OPTIMAL STOCK
A25: SKU-503 | B25: Chanderi Cotton Silk Kurta Set | C25: Women's Ethnic | D25: 110 | E25: 80 | F25: 100 | G25: 4500 | H25: =D25*G25 -> 495000 | I25: =IF(D25<=E25,"CRITICAL - REORDER NOW",IF(D25<=E25*1.25,"LOW STOCK - MONITOR","OPTIMAL STOCK")) -> OPTIMAL STOCK
A26: SKU-504 | B26: Kolhapuri Handcrafted Leather Footwear | C26: Footwear & Craft | D26: 25 | E26: 40 | F26: 75 | G26: 2800 | H26: =D26*G26 -> 70000 | I26: =IF(D26<=E26,"CRITICAL - REORDER NOW",IF(D26<=E26*1.25,"LOW STOCK - MONITOR","OPTIMAL STOCK")) -> CRITICAL - REORDER NOW
A27: SKU-505 | B27: Thanjavur Brass Puja Lamp (Diyas) | C27: Home & Heritage | D27: 65 | E27: 50 | F27: 60 | G27: 3200 | H27: =D27*G27 -> 208000 | I27: =IF(D27<=E27,"CRITICAL - REORDER NOW",IF(D27<=E27*1.25,"LOW STOCK - MONITOR","OPTIMAL STOCK")) -> OPTIMAL STOCK
A28: SKU-506 | B28: Organic Assam & Darjeeling Masala Chai | C28: Gourmet Beverages | D28: 210 | E28: 150 | F28: 200 | G28: 850 | H28: =D28*G28 -> 178500 | I28: =IF(D28<=E28,"CRITICAL - REORDER NOW",IF(D28<=E28*1.25,"LOW STOCK - MONITOR","OPTIMAL STOCK")) -> OPTIMAL STOCK
A29: SKU-507 | B29: Ayurvedic Herbal Skincare Gift Box | C29: Wellness & Care | D29: 35 | E29: 45 | F29: 80 | G29: 2200 | H29: =D29*G29 -> 77000 | I29: =IF(D29<=E29,"CRITICAL - REORDER NOW",IF(D29<=E29*1.25,"LOW STOCK - MONITOR","OPTIMAL STOCK")) -> CRITICAL - REORDER NOW
A30: SKU-508 | B30: Pure Copper Seamless Water Bottle (1L) | C30: Eco Home Ware | D30: 85 | E30: 60 | F30: 100 | G30: 1150 | H30: =D30*G30 -> 97750 | I30: =IF(D30<=E30,"CRITICAL - REORDER NOW",IF(D30<=E30*1.25,"LOW STOCK - MONITOR","OPTIMAL STOCK")) -> OPTIMAL STOCK
A31: SKU-509 | B31: Jaipuri Block-Print Double Bedspread | C31: Home Furnishings | D31: 18 | E31: 30 | F31: 50 | G31: 3800 | H31: =D31*G31 -> 68400 | I31: =IF(D31<=E31,"CRITICAL - REORDER NOW",IF(D31<=E31*1.25,"LOW STOCK - MONITOR","OPTIMAL STOCK")) -> CRITICAL - REORDER NOW
A32: SKU-510 | B32: Terracotta Handcrafted Cookware Set | C32: Artisanal Kitchen | D32: 48 | E32: 35 | F32: 60 | G32: 2900 | H32: =D32*G32 -> 139200 | I32: =IF(D32<=E32,"CRITICAL - REORDER NOW",IF(D32<=E32*1.25,"LOW STOCK - MONITOR","OPTIMAL STOCK")) -> OPTIMAL STOCK
A33: Total Inventory Value & Alerts | D33: =SUM(D23:D32) -> 656 | H33: =SUM(H23:H32) -> 2170850 | I33: =COUNTIF(I23:I32,"CRITICAL - REORDER NOW") & " Critical Items" -> 4 Critical Items

Sheet IBC_Executive_Dashboard
A1: AARAV RETAIL & LIFESTYLE INDIA LTD. - EXECUTIVE DECISION-MAKING DASHBOARD
A2: Integrated Business Case: Consolidated Performance, Sales Geography Ranking & Critical Inventory Scorecard
A4: Total Pan-India Retail Revenue | C4: Top Sales Performing City | E4: HR Performance Top Performers | G4: Total Employee Performance Bonus | I4: Critical Stock Alerts (Reorder Now)
A5: =IBC_Sales_and_Geography!G19 -> 217500000 | C5: Delhi NCR (₹3.85 Cr) | E5: =IBC_Employee_Performance!G5 -> 12 | G5: =IBC_Employee_Performance!I5 -> 750400 | I5: =IBC_Sales_and_Geography!I33 -> 4 Critical Items
A7: TOP 5 RETAIL & KEY ACCOUNT PERFORMERS (INDIA) | G7: TOP 5 BEST-SELLING RETAIL CITIES BY REVENUE (₹ INR)
A8: Rank | B8: Employee Name | C8: Base City | D8: Attainment % | E8: Performance Band | G8: Rank | H8: City | I8: State / UT | J8: Monthly Revenue (₹) | K8: YoY Growth %
A9: 1 | B9: =IBC_Employee_Performance!B10 -> Priya Nair | C9: =IBC_Employee_Performance!D10 -> Bengaluru | D9: =IBC_Employee_Performance!G10 -> 1.12 | E9: =IBC_Employee_Performance!K10 -> Top Performer | G9: 1 | H9: =IBC_Sales_and_Geography!A10 -> Delhi NCR | I9: =IBC_Sales_and_Geography!B10 -> Delhi | J9: =IBC_Sales_and_Geography!G10 -> 38500000 | K9: =IBC_Sales_and_Geography!I10 -> 0.15
A10: 2 | B10: =IBC_Employee_Performance!B19 -> Karthik Rajan | C10: =IBC_Employee_Performance!D19 -> Bengaluru | D10: =IBC_Employee_Performance!G19 -> 1.1 | E10: =IBC_Employee_Performance!K19 -> Top Performer | G10: 2 | H10: =IBC_Sales_and_Geography!A9 -> Mumbai | I10: =IBC_Sales_and_Geography!B9 -> Maharashtra | J10: =IBC_Sales_and_Geography!G9 -> 34800000 | K10: =IBC_Sales_and_Geography!I9 -> 0.18
A11: 3 | B11: =IBC_Employee_Performance!B15 -> Pooja Iyer | C11: =IBC_Employee_Performance!D15 -> Chennai | D11: =IBC_Employee_Performance!G15 -> 1.1 | E11: =IBC_Employee_Performance!K15 -> Top Performer | G11: 3 | H11: =IBC_Sales_and_Geography!A11 -> Bengaluru | I11: =IBC_Sales_and_Geography!B11 -> Karnataka | J11: =IBC_Sales_and_Geography!G11 -> 29600000 | K11: =IBC_Sales_and_Geography!I11 -> 0.22
A12: 4 | B12: =IBC_Employee_Performance!B9 -> Aarav Sharma | C12: =IBC_Employee_Performance!D9 -> Mumbai | D12: =IBC_Employee_Performance!G9 -> 1.15 | E12: =IBC_Employee_Performance!K9 -> Top Performer | G12: 4 | H12: =IBC_Sales_and_Geography!A13 -> Hyderabad | I12: =IBC_Sales_and_Geography!B13 -> Telangana | J12: =IBC_Sales_and_Geography!G13 -> 23200000 | K12: =IBC_Sales_and_Geography!I13 -> 0.21
A13: 5 | B13: =IBC_Employee_Performance!B13 -> Aditya Verma | C13: =IBC_Employee_Performance!D13 -> Delhi | D13: =IBC_Employee_Performance!G13 -> 1.08 | E13: =IBC_Employee_Performance!K13 -> Top Performer | G13: 5 | H13: =IBC_Sales_and_Geography!A14 -> Chennai | I13: =IBC_Sales_and_Geography!B14 -> Tamil Nadu | J13: =IBC_Sales_and_Geography!G14 -> 21800000 | K13: =IBC_Sales_and_Geography!I14 -> 0.14
